src/__init__.py
time_formatter-1.0.dist-info/METADATA
time_formatter-1.0.dist-info/WHEEL
time_formatter-1.0.dist-info/top_level.txt
time_formatter-1.0.dist-info/RECORD
