Metadata-Version: 2.1
Name: time-formatter
Version: 1.0
Summary: Universal time formatter, from seconds to %H:%M:%S format
Home-page: https://github.com/PanSageYT/time_formatter
Author: PanSage_
Author-email: root@pansage.xyz
Classifier: Programming Language :: Python :: 3
Classifier: License :: OSI Approved :: MIT License
Classifier: Operating System :: OS Independent
Requires-Python: >=3.7
